easy_database/__init__.py
easy_database/database.py
easy_database/utils.py
easy_database-1.1.8.dist-info/LICENSE
easy_database-1.1.8.dist-info/METADATA
easy_database-1.1.8.dist-info/WHEEL
easy_database-1.1.8.dist-info/entry_points.txt
easy_database-1.1.8.dist-info/top_level.txt
easy_database-1.1.8.dist-info/RECORD
