Metadata-Version: 2.1
Name: easy-database
Version: 1.1.8
Summary: abstraction for ETL Database interaction
Home-page: https://github.com/bclipp/easy_database
Author: Brian Lipp
Author-email: bclipp770@gmail.com
License: MIT
Platform: UNKNOWN
Classifier: License :: OSI Approved :: MIT License
Classifier: Programming Language :: Python
Classifier: Programming Language :: Python :: 3
Requires-Dist: pandas
Requires-Dist: psycopg2
